ValStorage/__init__.py
ValStorage/settings.py
ValStorage/storage.py
ValStorage-0.0.0.dist-info/LICENSE
ValStorage-0.0.0.dist-info/METADATA
ValStorage-0.0.0.dist-info/WHEEL
ValStorage-0.0.0.dist-info/top_level.txt
ValStorage-0.0.0.dist-info/RECORD
