Metadata-Version: 2.1
Name: ValStorage
Version: 0.0.0
Author: PWall
License: GPL-3.0
Project-URL: Homepage, https://github.com/ValUtils/ValStorage
Keywords: valorant,api,auth
Requires-Python: >=3.8
License-File: LICENSE
Requires-Dist: dataclasses-json
